<AAAInfo xmlns:dpfunc="http://www.datapower.com/extensions/functions" xmlns="http://www.datapower.com/AAAInfo">
	<FormatVersion>1</FormatVersion>
	<Filename>local:///IF_common/AUTH/WSP_PAPPIWPID01_AAAInfo.xml</Filename>
	<Summary>This is an example of the file format.</Summary>
	<!-- Determine credential from output of the extract-identity phase. -->
	<Authenticate>
		<Username>WSKEIBE</Username>
		<Password>aWJlcGlwcGFzc3dvcmQyNDY4</Password>
		<OutputCredential>admin</OutputCredential>
	</Authenticate>
	<Authenticate>
		<Username>KLS</Username>
		<Password>a2FsaXMxMjM=</Password>
		<OutputCredential>admin</OutputCredential>
	</Authenticate>
	<Authenticate>
		<Username>IVR</Username>
		<Password>aXBhc3N3b3JkaXZycGlwMQ==</Password>
		<OutputCredential>admin</OutputCredential>
	</Authenticate>
	<Authenticate>
		<Username>PNS</Username>
		<Password>cHBhc3N3b3JkcG5zcGlwMQ==</Password>
		<OutputCredential>admin</OutputCredential>
	</Authenticate>
	<Authenticate>
		<Username>FCM</Username>
		<Password>ZnBhc3N3b3JkZmNtcGlwMQ==</Password>
		<OutputCredential>admin</OutputCredential>
	</Authenticate>
	<Authenticate>
		<Username>WSKEIMM</Username>
		<Password>aW1tcGlwIyFwYXNzd29yZA==</Password>
		<OutputCredential>admin</OutputCredential>
	</Authenticate>
	<Authenticate>
		<Username>NAR</Username>
		<Password>bnBhc3N3b3JkbmFycGlwMQ==</Password>
		<OutputCredential>admin</OutputCredential>
	</Authenticate>
	<Authenticate>
		<Username>PCA</Username>
		<Password>cGNhcGlwIyFwYXNzd29yZA==</Password>
		<OutputCredential>admin</OutputCredential>
	</Authenticate>
	<Authenticate>
		<Username>VOC</Username>
		<Password>dm9jcGlwIyFwYXNzd29yZA0K</Password>
		<OutputCredential>admin</OutputCredential>
	</Authenticate>
	<Authenticate>
		<Username>ACP</Username>
		<Password>Y3Bhc3N3b3JkYWNzcGlwMQ==</Password>
		<OutputCredential>admin</OutputCredential>
	</Authenticate>
	<Authenticate>
		<Username>FID</Username>
		<Password>aXBhc3N3b3JkZmlkcGlwMQ==</Password>
		<OutputCredential>admin</OutputCredential>
	</Authenticate>
	<Authenticate>
		<Username>STF</Username>
		<Password>c3Bhc3N3b3Jkc3RmcGlwMQ==</Password>
		<OutputCredential>admin</OutputCredential>
	</Authenticate>
	<Authenticate>
		<Username>WLD</Username>
		<Password>d3Bhc3N3b3Jkd2xkcGlwMQ==</Password>
		<OutputCredential>admin</OutputCredential>
	</Authenticate>
	<Authenticate>
		<Username>WSKESLN</Username>
		<Password>d3NrZXNsbiMhcGFzc3dvcmQ=</Password>
		<OutputCredential>admin</OutputCredential>
	</Authenticate>
	<Authenticate>
		<Username>VIP</Username>
		<Password>dnBhc3N3b3JkdmlwcGlwMQ==</Password>
		<OutputCredential>admin</OutputCredential>
	</Authenticate>
	<Authenticate>
		<Username>HMP</Username>
		<Password>aHBncGlwIyFwYXNzd29yZA==</Password>
		<OutputCredential>admin</OutputCredential>
	</Authenticate>
	<Authenticate>
		<Username>GWP</Username>
		<Password>Z3dwcGlwIyFwYXNzd29yZA==</Password>
		<OutputCredential>admin</OutputCredential>
	</Authenticate>
	<Authenticate>
		<Username>CPS</Username>
		<Password>Y3Bhc3N3b3JkY3BzcGlwMQ==</Password>
		<OutputCredential>admin</OutputCredential>
	</Authenticate>		
</AAAInfo>